winpdb_rs-0.1.0.dist-info/METADATA
winpdb_rs-0.1.0.dist-info/WHEEL
winpdb_rs/__init__.py
winpdb_rs/winpdb_rs.cp311-win_amd64.pyd
winpdb_rs-0.1.0.dist-info/RECORD
