Metadata-Version: 2.4
Name: winpdb-rs
Version: 0.1.0
Summary: Bindingg for a Rust Parser for Microsoft PDB files
License: MIT
Requires-Python: >=3.8
Project-URL: Homepage, https://github.com/forentfraps/winpdb-rs
